tests/__init__.py
tests/test_scriptor.py
tube_scriptor/__init__.py
tube_scriptor/scriptor.py
tube_scriptor-2025.5.120740.dist-info/licenses/LICENSE
tube_scriptor-2025.5.120740.dist-info/METADATA
tube_scriptor-2025.5.120740.dist-info/WHEEL
tube_scriptor-2025.5.120740.dist-info/top_level.txt
tube_scriptor-2025.5.120740.dist-info/RECORD
